subtitlecore/__init__.py
subtitlecore/constants.py
subtitlecore/entry.py
subtitlecore/sentencizer.py
subtitlecore/subtitle.py
subtitlecore-0.1.16.dist-info/METADATA
subtitlecore-0.1.16.dist-info/WHEEL
subtitlecore-0.1.16.dist-info/entry_points.txt
subtitlecore-0.1.16.dist-info/RECORD
