Metadata-Version: 2.1
Name: subtitlecore
Version: 0.1.16
Summary: Parse srt file content into well-formed structures
Home-page: https://github.com/qishe-nlp/subtitlecore
Keywords: subtitle,parse,srt
Author: Phoenix.Grey
Author-email: phoenix.grey0108@gmail.com
Requires-Python: >=3.12,<4.0
Classifier: Programming Language :: Python :: 3
Classifier: Programming Language :: Python :: 3.12
Classifier: Programming Language :: Python :: 3.13
Requires-Dist: click (>=8.0.3,<9.0.0)
Requires-Dist: spacy (==3.7.5)
Requires-Dist: webvtt-py (>=0.4.3,<0.5.0)
Project-URL: Documentation, https://qishe-nlp.github.io/subtitlecore/
Project-URL: Repository, https://github.com/qishe-nlp/subtitlecore
